django_opentracing/__init__.py
django_opentracing/_version.py
django_opentracing/middleware.py
django_opentracing/tracing.py
tests/manage.py
django_opentracing-1.1.0.dist-info/LICENSE
django_opentracing-1.1.0.dist-info/METADATA
django_opentracing-1.1.0.dist-info/WHEEL
django_opentracing-1.1.0.dist-info/top_level.txt
django_opentracing-1.1.0.dist-info/RECORD
