Metadata-Version: 2.1
Name: django-opentracing
Version: 1.1.0
Summary: OpenTracing support for Django applications
Home-page: https://github.com/opentracing-contrib/python-django/
Author: Kathy Camenzind
Author-email: kcamenzind@lightstep.com
License: BSD
Download-URL: https://github.com/opentracing-contrib/python-django/tarball/1.1.0
Platform: any
Classifier: Environment :: Web Environment
Classifier: Intended Audience :: Developers
Classifier: License :: OSI Approved :: BSD License
Classifier: Operating System :: OS Independent
Classifier: Framework :: Django :: 1.11
Classifier: Framework :: Django :: 2.1
Classifier: Framework :: Django :: 2.2
Classifier: Programming Language :: Python
Classifier: Programming Language :: Python :: 2.7
Classifier: Programming Language :: Python :: 3.5
Classifier: Programming Language :: Python :: 3.6
Classifier: Programming Language :: Python :: 3.7
Classifier: Topic :: Internet :: WWW/HTTP :: Dynamic Content
Classifier: Topic :: Software Development :: Libraries :: Python Modules
Provides-Extra: tests
